geopointdb/__init__.py
geopointdb/getpoint.py
geopointdb/worldcities.db
geopointdb-1.2.0.dist-info/licenses/LICENSE
geopointdb-1.2.0.dist-info/METADATA
geopointdb-1.2.0.dist-info/WHEEL
geopointdb-1.2.0.dist-info/top_level.txt
geopointdb-1.2.0.dist-info/RECORD
