Metadata-Version: 2.4
Name: geopointdb
Version: 1.2.0
Summary: Offline geolocation and geocoding package using SQLite (~200000+ world cities)
Home-page: https://github.com/Pulkit-Py/geopointdb
Author: Pulkit Saini
Author-email: Pulkit Saini <pulkitsaini127@gmail.com>
License: MIT
Project-URL: Homepage, https://github.com/Pulkit-Py/geopointdb
Project-URL: Repository, https://github.com/Pulkit-Py/geopointdb/issues
Keywords: geolocation,geocoding,sqlite,offline,world cities
Classifier: Development Status :: 4 - Beta
Classifier: Intended Audience :: Developers
Classifier: Topic :: Software Development :: Libraries :: Python Modules
Classifier: Topic :: Database :: Database Engines/Servers
Classifier: Topic :: Utilities
Classifier: Programming Language :: Python :: 3
Classifier: Programming Language :: Python :: 3.7
Classifier: Programming Language :: Python :: 3.8
Classifier: Programming Language :: Python :: 3.9
Classifier: Programming Language :: Python :: 3.10
Classifier: Programming Language :: Python :: 3.11
Classifier: Programming Language :: Python :: 3.12
Classifier: License :: OSI Approved :: MIT License
Classifier: Operating System :: OS Independent
Requires-Python: >=3.7
License-File: LICENSE
Provides-Extra: dev
Requires-Dist: pytest>=6.0; extra == "dev"
Requires-Dist: pytest-cov>=2.0; extra == "dev"
Requires-Dist: black>=22.0; extra == "dev"
Requires-Dist: isort>=5.0; extra == "dev"
Requires-Dist: flake8>=3.9; extra == "dev"
Dynamic: license-file
